stayawake/__init__.py
stayawake/cli.py
stayawake-0.1.0.dist-info/LICENSE
stayawake-0.1.0.dist-info/METADATA
stayawake-0.1.0.dist-info/WHEEL
stayawake-0.1.0.dist-info/entry_points.txt
stayawake-0.1.0.dist-info/top_level.txt
stayawake-0.1.0.dist-info/RECORD
